pecoregex/__init__.py
pecoregex/__main__.py
pecoregex/cli.py
pecoregex/document.py
pecoregex/extproc.py
pecoregex/factory.py
pecoregex/pcre.py
pecoregex/util.py
pecoregex-1.1.0.dist-info/LICENSE.txt
pecoregex-1.1.0.dist-info/METADATA
pecoregex-1.1.0.dist-info/WHEEL
pecoregex-1.1.0.dist-info/entry_points.txt
pecoregex-1.1.0.dist-info/top_level.txt
pecoregex-1.1.0.dist-info/RECORD
