Metadata-Version: 2.1
Name: pecoregex
Version: 1.1.0
Summary: Evaluate Perl-Compatible Regular Expressions
Home-page: https://github.com/xavierog/pecoregex
Author: Xavier G.
Author-email: xavier.pecoregex@kindwolf.org
License: BSD
Keywords: regex,pcre,ctypes,cli,json,yaml
Platform: UNKNOWN
Classifier: License :: OSI Approved :: BSD License
Classifier: Operating System :: POSIX :: Linux
Classifier: Programming Language :: Python :: 3 :: Only
Classifier: Topic :: Text Processing
License-File: LICENSE.txt
Requires-Dist: pyyaml
